jmq_krill/__init__.py
jmq_krill/krill_api.py
jmq_krill-0.2.0.dist-info/licenses/LICENSE
jmq_krill-0.2.0.dist-info/METADATA
jmq_krill-0.2.0.dist-info/WHEEL
jmq_krill-0.2.0.dist-info/top_level.txt
jmq_krill-0.2.0.dist-info/RECORD
